{
  "linux": {
    "text": "Linux",
    "base": "/system/linux/",
    "children": [
      {
        "text": "常用命令",
        "link": "common-commands"
      },
      {
        "text": "常见问题",
        "link": "common-faq"
      },
      {
        "text": "Docker镜像源",
        "link": "docker-mirror"
      },
      {
        "text": "WSL迁移",
        "link": "wsl-migration"
      },
      {
        "text": "日志管理脚本",
        "link": "log-management-scripts"
      },
      {
        "text": "FFmpeg安装使用",
        "link": "ffmpeg"
      }
    ]
  },
  "windows": {
    "text": "Windows",
    "base": "/system/windows/",
    "children": [
      {
        "text": "常用命令",
        "link": "common-commands"
      }
    ]
  }
}
